spar/__init__.py
spar/__main__.py
spar/cli.py
spar/generate.py
spar/io.py
spar/progress.py
spar/transform.py
spar/utils.py
spar/data/distributions/cpl_dist.pkl
spar/data/distributions/instance_cpu_dist.pkl
spar/data/distributions/instance_duration_dist.pkl
spar/data/distributions/instance_mem_dist.pkl
spar/data/distributions/instance_num_dist.pkl
spar/data/distributions/job_interval_dist.pkl
spar/data/distributions/level_dist.pkl
spar/data/distributions/task_cpu_dist.pkl
spar/data/distributions/task_duration_dist.pkl
spar/data/distributions/task_mem_dist.pkl
spar/data/distributions/task_num_dist.pkl
spar/data/samples/sample_instances.csv
spar/data/samples/sample_tasks.csv
spar-0.0.7.dist-info/LICENSE
spar-0.0.7.dist-info/METADATA
spar-0.0.7.dist-info/WHEEL
spar-0.0.7.dist-info/entry_points.txt
spar-0.0.7.dist-info/top_level.txt
spar-0.0.7.dist-info/RECORD
