Metadata-Version: 2.1
Name: spar
Version: 0.0.7
Summary: A CLI tool for generating controllable cluster trace.
Home-page: https://github.com/All-less/trace-generator
Author: All-less
Author-email: all.less.mail@gmail.com
License: MIT
Keywords: cluster trace,cloud computing
Platform: UNKNOWN
Classifier: License :: OSI Approved :: MIT License
Classifier: Programming Language :: Python :: 3.6
Classifier: Programming Language :: Python :: 3.7
Requires-Dist: click
Requires-Dist: scipy
Requires-Dist: crayons
Requires-Dist: numpy
